LICENSE
README.md
smartfaker/__init__.py
smartfaker/fake.py
smartfaker/iban.py
smartfaker/data/ad.json
smartfaker/data/ae.json
smartfaker/data/af.json
smartfaker/data/ag.json
smartfaker/data/ai.json
smartfaker/data/al.json
smartfaker/data/am.json
smartfaker/data/aq.json
smartfaker/data/ar.json
smartfaker/data/at.json
smartfaker/data/au.json
smartfaker/data/aw.json
smartfaker/data/az.json
smartfaker/data/azw.json
smartfaker/data/ba.json
smartfaker/data/bb.json
smartfaker/data/bd.json
smartfaker/data/be.json
smartfaker/data/bg.json
smartfaker/data/bh.json
smartfaker/data/bj.json
smartfaker/data/bm.json
smartfaker/data/bn.json
smartfaker/data/bo.json
smartfaker/data/br.json
smartfaker/data/bs.json
smartfaker/data/bt.json
smartfaker/data/bw.json
smartfaker/data/by.json
smartfaker/data/bz.json
smartfaker/data/ca.json
smartfaker/data/cf.json
smartfaker/data/ch.json
smartfaker/data/cl.json
smartfaker/data/cm.json
smartfaker/data/cn.json
smartfaker/data/co.json
smartfaker/data/cr.json
smartfaker/data/cu.json
smartfaker/data/cv.json
smartfaker/data/cy.json
smartfaker/data/cz.json
smartfaker/data/de.json
smartfaker/data/dj.json
smartfaker/data/dk.json
smartfaker/data/dm.json
smartfaker/data/do.json
smartfaker/data/dz.json
smartfaker/data/ec.json
smartfaker/data/ee.json
smartfaker/data/eg.json
smartfaker/data/er.json
smartfaker/data/es.json
smartfaker/data/fi.json
smartfaker/data/fj.json
smartfaker/data/fm.json
smartfaker/data/fr.json
smartfaker/data/ga.json
smartfaker/data/gb.json
smartfaker/data/ge.json
smartfaker/data/gh.json
smartfaker/data/gl.json
smartfaker/data/gm.json
smartfaker/data/gn.json
smartfaker/data/gr.json
smartfaker/data/gt.json
smartfaker/data/gw.json
smartfaker/data/gy.json
smartfaker/data/hk.json
smartfaker/data/hr.json
smartfaker/data/ht.json
smartfaker/data/hu.json
smartfaker/data/id.json
smartfaker/data/ie.json
smartfaker/data/il.json
smartfaker/data/in.json
smartfaker/data/iq.json
smartfaker/data/is.json
smartfaker/data/it.json
smartfaker/data/jm.json
smartfaker-3.25.1.dist-info/METADATA
smartfaker-3.25.1.dist-info/WHEEL
smartfaker-3.25.1.dist-info/licenses/LICENSE
smartfaker-3.25.1.dist-info/RECORD
