Metadata-Version: 2.4
Name: smartfaker
Version: 3.25.1
Summary: A powerful Asynchronous Python library for generating fake addresses and IBANs, supporting bots, MTProto API frameworks, and Python scripts
Project-URL: Homepage, https://github.com/abirxdhack/TheSmartFaker
Project-URL: Documentation, https://abirxdhack.github.io/SmartFakerDocs
Project-URL: Source, https://github.com/abirxdhack/TheSmartFaker
Project-URL: Tracker, https://github.com/abirxdhack/TheSmartFaker/issues
Project-URL: Changelog, https://github.com/abirxdhack/TheSmartFaker/releases
Author-email: ISmartCoder <abrixdhackz.info.me@gmail.com>
License: MIT
License-File: LICENSE
Keywords: address-generator,fake-data,faker,iban-generator,mtproto,python-library,telegram-bot
Classifier: License :: OSI Approved :: MIT License
Classifier: Programming Language :: Python :: 3.8
Classifier: Programming Language :: Python :: 3.9
Classifier: Programming Language :: Python :: 3.10
Classifier: Programming Language :: Python :: 3.11
Classifier: Programming Language :: Python :: 3.12
Classifier: Topic :: Software Development :: Libraries
Requires-Python: >=3.8
Requires-Dist: pycountry
